{
    "configurations": [
        {
            "name": "Android ARM64",
            "includePath": [
                "${workspaceFolder}/app/src/main/cpp",
                "${workspaceFolder}/app/src/main/cpp/whisper.cpp/include",
                "${env:LOCALAPPDATA}/Android/Sdk/ndk/28.2.13676358/toolchains/llvm/prebuilt/windows-x86_64/sysroot/usr/include",
                "${env:LOCALAPPDATA}/Android/Sdk/ndk/28.2.13676358/toolchains/llvm/prebuilt/windows-x86_64/sysroot/usr/include/aarch64-linux-android"
            ],
            "defines": [
                "__ANDROID__",
                "ANDROID",
                "__ANDROID_API__=33",
                "__aarch64__"
            ],
            "compilerPath": "${env:LOCALAPPDATA}/Android/Sdk/ndk/28.2.13676358/toolchains/llvm/prebuilt/windows-x86_64/bin/aarch64-linux-android33-clang++",
            "cStandard": "c17",
            "cppStandard": "c++20",
            "intelliSenseMode": "linux-clang-arm64"
        }
    ],
    "version": 4
}
